{
  "firstname": "Joe",
  "lastname": "Rogers",
  "handle": "Selir",
  "birth": "1974",
  "death": "2019",
  "obituary": "https://loylessfuneralhomes.com/tribute/details/140691/Joseph-Rogers-III/obituary.html",
  "issue": "19",
  "affiliations": "Legitimate Business Syndicate, University of South Florida",
  "mainimage": "/images/JoeRogers2.jpg",
  "maintext": "<p>Joseph Hinton Rogers III, known as Selir, was born May 4, 1974 in Lakeland, Florida. He earned two bachelor's degrees in Computer Science and Computer Engineering, as well as a master's degree in Computer Engineering, all from the University of South Florida. Joe worked as a network administrator at USF for 25 years.</p><p>He was a member of the Legitimate Business Syndicate CTF team at DEF CON for five to six years, earning six to seven black badges. His handle \"Selir\" came from a Pathfinder character he played. Joe was an avid biker and tabletop gamer.</p><p>Joe passed away on June 12, 2019 after a two-and-a-half-year battle with colon cancer. He is survived by his wife.</p>",
  "socialmedialinks": [],
  "contributions": [],
  "gallery": [
    {
      "url": "/images/JoeRogers1.jpg",
      "title": "",
      "caption": "Photo provided by his widow"
    }
  ]
}
